DC_OCEAN/Duplicate_Checker.py
DC_OCEAN/M00_Duplicate_Check_MAIN.py
DC_OCEAN/__init__.py
DC_OCEAN/Input_files/DuplicateList_sorted_unique_pairs_generic.txt
DC_OCEAN/Input_files/Unduplicatelist_sorted_unique_pairs_generic.txt
DC_OCEAN/Input_files/sorted_unique_pairs_generic.txt
DC_OCEAN/Input_files/WOD18_sample_1995/wod_004181522O.nc
DC_OCEAN/Input_files/WOD18_sample_1995/wod_004181523O.nc
DC_OCEAN/Input_files/WOD18_sample_1995/wod_004181524O.nc
DC_OCEAN/Input_files/WOD18_sample_1995/wod_004181525O.nc
DC_OCEAN/Input_files/WOD18_sample_1995/wod_004181526O.nc
DC_OCEAN/Input_files/WOD18_sample_1995/wod_004181527O.nc
DC_OCEAN/Input_files/WOD18_sample_1995/wod_007274385O.nc
DC_OCEAN/Input_files/WOD18_sample_1995/wod_007274386O.nc
DC_OCEAN/Input_files/WOD18_sample_1995/wod_007274387O.nc
DC_OCEAN/Input_files/WOD18_sample_1995/wod_007274388O.nc
DC_OCEAN/Input_files/WOD18_sample_1995/wod_007274389O.nc
DC_OCEAN/Input_files/WOD18_sample_1995/wod_007274390O.nc
DC_OCEAN/Input_files/WOD18_sample_1995/wod_007274391O.nc
DC_OCEAN/Input_files/WOD18_sample_1995/wod_007274392O.nc
DC_OCEAN/Input_files/WOD18_sample_1995/wod_007274393O.nc
DC_OCEAN/Input_files/WOD18_sample_1995/wod_007274394O.nc
DC_OCEAN/Input_files/WOD18_sample_1995/wod_007274395O.nc
DC_OCEAN/Input_files/WOD18_sample_1995/wod_007274396O.nc
DC_OCEAN/Input_files/WOD18_sample_1995/wod_007274397O.nc
DC_OCEAN/Input_files/WOD18_sample_1995/wod_007274398O.nc
DC_OCEAN/Input_files/WOD18_sample_1995/wod_007274399O.nc
DC_OCEAN/Input_files/WOD18_sample_1995/wod_007274400O.nc
DC_OCEAN/Input_files/WOD18_sample_1995/wod_007274401O.nc
DC_OCEAN/Input_files/WOD18_sample_1995/wod_007274402O.nc
DC_OCEAN/Input_files/WOD18_sample_1995/wod_007274403O.nc
DC_OCEAN/Input_files/WOD18_sample_1995/wod_007274404O.nc
DC_OCEAN/Input_files/WOD18_sample_1995/wod_007274405O.nc
DC_OCEAN/Input_files/WOD18_sample_1995/wod_007274406O.nc
DC_OCEAN/Input_files/WOD18_sample_1995/wod_007274407O.nc
DC_OCEAN/Input_files/WOD18_sample_1995/wod_007274408O.nc
DC_OCEAN-1.3.2.dist-info/LICENSE
DC_OCEAN-1.3.2.dist-info/METADATA
DC_OCEAN-1.3.2.dist-info/WHEEL
DC_OCEAN-1.3.2.dist-info/top_level.txt
DC_OCEAN-1.3.2.dist-info/RECORD
