Metadata-Version: 2.1
Name: DC-OCEAN
Version: 1.3.2
Summary: DC_OCEAN: An algorithm to detect the ocean in-situ duplicate profiles (Song et al., 2024, FMS)
Home-page: https://github.com/IQuOD/duplicated_checking_IQuOD/
Author: Zhetao Tan; Xinyi Song, Lijing Cheng, Rebecca Cowley, Huifeng Yuan, Guilherme Castelao, Simona Simoncelli, Shoichi Kizu, Ricardo Locarnini, Tim Boyer, Franco Reseghetti, Viktor Gouretski
Author-email: tanzhetao@mail.iap.ac.cn; songxinyi231@mails.ucas.ac.cn
Classifier: Programming Language :: Python :: 3
Classifier: License :: OSI Approved :: Apache Software License
Classifier: Operating System :: OS Independent
Requires-Python: >=3.8
License-File: LICENSE
Requires-Dist: numpy >=1.19.1
Requires-Dist: netCDF4 >=1.5.4
Requires-Dist: timezonefinder >=6.0.1
Requires-Dist: pandas >=1.0.3
Requires-Dist: scipy >=1.7.3
Requires-Dist: argparse >=1.4.0
